[
  
  {
    "id": "mh54qw2i7KPJA",
    "name": "Đi chơi",
    "description": "D&T",
    "createdBy": "uj2c0n67k",
    "createdAt": "2025-10-24T17:33:33.786Z",
    "members": [
      "uj2c0n67k",
      "mh54sgj25TH3H"
    ],
    "expenses": [
      "mh54rnc1YTLA6"
    ],
    "joinCode": "S78OOM"
  },
  {
    "id": "mhuw0k5bQ1OU3",
    "name": "Đi Ăn ",
    "description": "",
    "createdBy": "mh54sgj25TH3H",
    "createdAt": "2025-11-11T18:11:08.927Z",
    "members": [
      "mh54sgj25TH3H",
      "mhuw1z8uUDQGD"
    ],
    "expenses": [
      "mhuw6ywlC5FNF"
    ],
    "joinCode": "F9PRRU"
  }
]